mewtocol_ex/__about__.py
mewtocol_ex/__init__.py
mewtocol_ex/main.py
mewtocol_ex-0.0.1.dist-info/METADATA
mewtocol_ex-0.0.1.dist-info/WHEEL
mewtocol_ex-0.0.1.dist-info/licenses/LICENSE.txt
mewtocol_ex-0.0.1.dist-info/RECORD
